{"cameraMode":{"drawMode":0,"name":"Shaded","section":"Shading Mode"},"sceneLighting":true,"audioPlay":false,"sceneViewState":{"showFog":true,"showMaterialUpdate":false,"showSkybox":true,"showFlares":true,"showImageEffects":true,"showParticleSystems":true},"in2DMode":false,"pivot":{"x":-72.28897857666016,"y":-150.30528259277345,"z":108.86836242675781},"rotation":{"x":-0.29954689741134646,"y":0.47860804200172427,"z":-0.18179866671562196,"w":-0.805485725402832},"size":193.2899627685547,"orthographic":false}