{"cameraMode":{"drawMode":0,"name":"Shaded","section":"Shading Mode"},"sceneLighting":true,"audioPlay":false,"sceneViewState":{"showFog":true,"showMaterialUpdate":false,"showSkybox":true,"showFlares":true,"showImageEffects":true,"showParticleSystems":true},"in2DMode":false,"pivot":{"x":-172.92343139648438,"y":4.487393856048584,"z":-7.578648567199707},"rotation":{"x":0.1504502147436142,"y":-0.6262906789779663,"z":0.12491265684366226,"w":0.7546991109848023},"size":2.89947509765625,"orthographic":false}